semmo/__init__.py
semmo/semmo.py
semmo-0.0.3.dist-info/LICENSE
semmo-0.0.3.dist-info/METADATA
semmo-0.0.3.dist-info/WHEEL
semmo-0.0.3.dist-info/top_level.txt
semmo-0.0.3.dist-info/RECORD
